japan_geoid-0.6.0.dist-info/METADATA
japan_geoid-0.6.0.dist-info/WHEEL
japan_geoid-0.6.0.dist-info/licenses/LICENSE.txt
japan_geoid.libs/libgcc_s-27e5a392.so.1
japan_geoid/__init__.py
japan_geoid/__init__.pyi
japan_geoid/japan_geoid.cpython-313-i386-linux-musl.so
japan_geoid/py.typed
japan_geoid-0.6.0.dist-info/RECORD
