Metadata-Version: 2.4
Name: japan-geoid
Version: 0.6.0
Classifier: License :: OSI Approved :: MIT License
Classifier: Programming Language :: Python :: Implementation :: CPython
Classifier: Programming Language :: Python :: Implementation :: PyPy
Classifier: Programming Language :: Rust
Classifier: Topic :: Scientific/Engineering :: GIS
License-File: LICENSE.txt
Summary: Calculate geoid heights for Japan using GSI's geoid model.
Author-email: Taku Fukada <naninunenor@gmail.com>
License-Expression: MIT
Requires-Python: >=3.9
Project-URL: repository, https://github.com/ciscorn/japan-geoid/
